pmma/__init__.py
pmma/py.typed
pmma/build/AdvancedMathematics.cpython-310-x86_64-linux-gnu.so
pmma/build/AdvancedMathematics.pyi
pmma/build/Animation.cpython-310-x86_64-linux-gnu.so
pmma/build/Animation.pyi
pmma/build/ControllerEvents.cpython-310-x86_64-linux-gnu.so
pmma/build/ControllerEvents.pyi
pmma/build/Display.cpython-310-x86_64-linux-gnu.so
pmma/build/Display.pyi
pmma/build/FractalBrownianMotion.cpython-310-x86_64-linux-gnu.so
pmma/build/FractalBrownianMotion.pyi
pmma/build/General.cpython-310-x86_64-linux-gnu.so
pmma/build/General.pyi
pmma/build/KeyEvents.cpython-310-x86_64-linux-gnu.so
pmma/build/KeyEvents.pyi
pmma/build/KeyPadEvents.cpython-310-x86_64-linux-gnu.so
pmma/build/KeyPadEvents.pyi
pmma/build/Logger.cpython-310-x86_64-linux-gnu.so
pmma/build/Logger.pyi
pmma/build/MouseEvents.cpython-310-x86_64-linux-gnu.so
pmma/build/MouseEvents.pyi
pmma/build/NumberFormats.cpython-310-x86_64-linux-gnu.so
pmma/build/NumberFormats.pyi
pmma/build/PMMA_Core.cpython-310-x86_64-linux-gnu.so
pmma/build/PMMA_Core.pyi
pmma/build/Passport.cpython-310-x86_64-linux-gnu.so
pmma/build/Passport.pyi
pmma/build/PerlinNoise.cpython-310-x86_64-linux-gnu.so
pmma/build/PerlinNoise.pyi
pmma/build/Shapes2D.cpython-310-x86_64-linux-gnu.so
pmma/build/Shapes2D.pyi
pmma/build/TextRenderer.cpython-310-x86_64-linux-gnu.so
pmma/build/TextRenderer.pyi
pmma/build/WindowEvents.cpython-310-x86_64-linux-gnu.so
pmma/build/WindowEvents.pyi
pmma/config/update_config.json
pmma/core/py_src/AdvancedThreading.py
pmma/core/py_src/AdvancedThreading.pyi
pmma/core/py_src/AdvancedTkinter.py
pmma/core/py_src/AdvancedTkinter.pyi
pmma/core/py_src/Audio.py
pmma/core/py_src/Audio.pyi
pmma/core/py_src/Backpack.py
pmma/core/py_src/Backpack.pyi
pmma/core/py_src/Constants.py
pmma/core/py_src/Constants.pyi
pmma/core/py_src/DataStructures.py
pmma/core/py_src/DataStructures.pyi
pmma/core/py_src/DateTimeFormatter.py
pmma/core/py_src/DateTimeFormatter.pyi
pmma/core/py_src/Error.py
pmma/core/py_src/Error.pyi
pmma-5.0.16.dist-info/licenses/LICENSE.md
pmma-5.0.16.dist-info/METADATA
pmma-5.0.16.dist-info/WHEEL
pmma-5.0.16.dist-info/top_level.txt
pmma-5.0.16.dist-info/RECORD
