Metadata-Version: 2.4
Name: pmma
Version: 5.0.16
Summary: Python Multi-Media API (PMMA) is a multi-purpose API designed to make working on multi-media projects easier and faster!
Home-page: https://github.com/PycraftDeveloper/PMMA
Author: PycraftDev
Author-email: thomasjebbo@gmail.com
Project-URL: Bug Tracker, https://github.com/PycraftDeveloper/PMMA/issues
Classifier: Development Status :: 3 - Alpha
Classifier: Environment :: Console
Classifier: Environment :: Win32 (MS Windows)
Classifier: Environment :: X11 Applications
Classifier: Intended Audience :: Developers
Classifier: Intended Audience :: End Users/Desktop
Classifier: Intended Audience :: Information Technology
Classifier: Intended Audience :: Other Audience
Classifier: Intended Audience :: Science/Research
Classifier: License :: OSI Approved :: MIT License
Classifier: Natural Language :: English
Classifier: Operating System :: Microsoft :: Windows :: Windows 8
Classifier: Operating System :: Microsoft :: Windows :: Windows 8.1
Classifier: Operating System :: Microsoft :: Windows :: Windows 10
Classifier: Operating System :: Microsoft :: Windows :: Windows 11
Classifier: Operating System :: POSIX :: Linux
Classifier: Programming Language :: C++
Classifier: Programming Language :: Python :: 3.8
Classifier: Programming Language :: Python :: 3.9
Classifier: Programming Language :: Python :: 3.10
Classifier: Programming Language :: Python :: 3.11
Classifier: Topic :: Artistic Software
Classifier: Topic :: Desktop Environment
Classifier: Topic :: Games/Entertainment
Classifier: Topic :: Multimedia
Classifier: Topic :: Scientific/Engineering :: Visualization
Classifier: Topic :: Software Development
Classifier: Topic :: System
Classifier: Topic :: Utilities
Classifier: Typing :: Stubs Only
Requires-Python: >=3.8
License-File: LICENSE.md
Requires-Dist: numpy>=2.0
Requires-Dist: pedalboard
Requires-Dist: pprofile
Requires-Dist: pyadl
Requires-Dist: requests
Requires-Dist: send2trash
Requires-Dist: sounddevice
Requires-Dist: soundfile
Requires-Dist: waiting
Requires-Dist: pywin32; sys_platform == "win32"
Requires-Dist: wmi; sys_platform == "win32"
Dynamic: author
Dynamic: author-email
Dynamic: classifier
Dynamic: description
Dynamic: description-content-type
Dynamic: home-page
Dynamic: license-file
Dynamic: project-url
Dynamic: requires-dist
Dynamic: requires-python
Dynamic: summary
